dff_calc/__init__.py
dff_calc/df_f_calculation.py
dff_calc-0.2.0.dist-info/LICENSE.md
dff_calc-0.2.0.dist-info/WHEEL
dff_calc-0.2.0.dist-info/METADATA
dff_calc-0.2.0.dist-info/RECORD
